{
    "last_update": 1726948413,
    "grouped_data": [
        {
            "district": "Districts_f",
            "total_votes": "41067",
            "total_disable_votes": "927",
            "valid_votes": "40140",
            "uptime": "2024-09-22 01:23:31",
            "parties": [
                {
                    "name": "Sajith",
                    "total": "5338",
                    "percentage": "13.30"
                },
                {
                    "name": "Ranil",
                    "total": "5338",
                    "percentage": "13.30"
                },
                {
                    "name": "Anura",
                    "total": "25892",
                    "percentage": "64.50"
                },
                {
                    "name": "Namal",
                    "total": "863",
                    "percentage": "2.15"
                },
                {
                    "name": "Others",
                    "total": "2709",
                    "percentage": "6.75"
                }
            ]
        },
        {
            "district": "Districts_h",
            "total_votes": "21998",
            "total_disable_votes": "449",
            "valid_votes": "21549",
            "uptime": "2024-09-22 01:16:24",
            "parties": [
                {
                    "name": "Sajith",
                    "total": "3397",
                    "percentage": "15.76"
                },
                {
                    "name": "Ranil",
                    "total": "2502",
                    "percentage": "11.61"
                },
                {
                    "name": "Anura",
                    "total": "14482",
                    "percentage": "67.20"
                },
                {
                    "name": "Namal",
                    "total": "819",
                    "percentage": "3.80"
                },
                {
                    "name": "Others",
                    "total": "967",
                    "percentage": "4.49"
                }
            ]
        },
        {
            "district": "Districts_q",
            "total_votes": "24544",
            "total_disable_votes": "555",
            "valid_votes": "23989",
            "uptime": "2024-09-22 01:22:16",
            "parties": [
                {
                    "name": "Sajith",
                    "total": "5733",
                    "percentage": "23.90"
                },
                {
                    "name": "Ranil",
                    "total": "3401",
                    "percentage": "14.18"
                },
                {
                    "name": "Anura",
                    "total": "14050",
                    "percentage": "58.57"
                },
                {
                    "name": "Namal",
                    "total": "470",
                    "percentage": "1.96"
                },
                {
                    "name": "Others",
                    "total": "335",
                    "percentage": "1.40"
                }
            ]
        },
        {
            "district": "Districts_t",
            "total_votes": "19583",
            "total_disable_votes": "372",
            "valid_votes": "19211",
            "uptime": "2024-09-22 01:14:54",
            "parties": [
                {
                    "name": "Sajith",
                    "total": "4120",
                    "percentage": "21.45"
                },
                {
                    "name": "Ranil",
                    "total": "2762",
                    "percentage": "14.38"
                },
                {
                    "name": "Anura",
                    "total": "11768",
                    "percentage": "61.26"
                },
                {
                    "name": "Namal",
                    "total": "188",
                    "percentage": "0.98"
                },
                {
                    "name": "Others",
                    "total": "373",
                    "percentage": "1.94"
                }
            ]
        },
        {
            "district": "Districts_v",
            "total_votes": "32179",
            "total_disable_votes": "640",
            "valid_votes": "31539",
            "uptime": "2024-09-22 00:07:32",
            "parties": [
                {
                    "name": "Sajith",
                    "total": "4675",
                    "percentage": "14.82"
                },
                {
                    "name": "Ranil",
                    "total": "6641",
                    "percentage": "21.06"
                },
                {
                    "name": "Anura",
                    "total": "19185",
                    "percentage": "60.83"
                },
                {
                    "name": "Namal",
                    "total": "500",
                    "percentage": "1.59"
                },
                {
                    "name": "Others",
                    "total": "538",
                    "percentage": "1.71"
                }
            ]
        }
    ]
}
